medflux/__init__.py
medflux/datasets/__init__.py
medflux/datasets/data_collator.py
medflux/datasets/encoders.py
medflux/datasets/filters.py
medflux/datasets/patient_concept_stream.py
medflux/datasets/preprocessing.py
medflux/datasets/tokenizers.py
medflux/datasets/utils.py
medflux/metrics/__init__.py
medflux/metrics/next_concept_prediction.py
medflux/models/__init__.py
medflux/models/lucid_transformers.py
medflux/utils/pickle.py
medgpt/__init__.py
medgpt/data_transfer.py
medgpt/foresight.py
medgpt/datasets/__init__.py
medgpt/datasets/data_collator.py
medgpt/datasets/filters.py
medgpt/datasets/patient_concept_stream.py
medgpt/datasets/tokenizers.py
medgpt/datasets/utils.py
medgpt/metrics/__init__.py
medgpt/metrics/next_concept_prediction.py
medgpt/models/__init__.py
medgpt/models/lucid_transformers.py
medgpt/tokenizers/simple_map_tokenizer.py
medgpt/utils/cdb_utils.py
medgpt/utils/pickle.py
medgpt/utils/stream_utils.py
medgpt-0.3.3.dist-info/medflux.egg-info/dependency_links.txt
medgpt-0.3.3.dist-info/medflux.egg-info/top_level.txt
medgpt-0.3.3.dist-info/METADATA
medgpt-0.3.3.dist-info/WHEEL
medgpt-0.3.3.dist-info/top_level.txt
medgpt-0.3.3.dist-info/RECORD
