Metadata-Version: 2.1
Name: medgpt
Version: 0.3.3
Summary: Temporal modeling of patients and diseases
Home-page: https://github.com/w-is-h/medgpt
Author: w-is-h
Author-email: w.kraljevic@gmail.com
License: UNKNOWN
Platform: UNKNOWN
Classifier: Programming Language :: Python :: 3
Classifier: License :: OSI Approved :: MIT License
Classifier: Operating System :: OS Independent
Requires-Dist: datasets (~=1.14.0)
Requires-Dist: ray (>=1.3.0)
Requires-Dist: wandb (<1.0,>=0.10)
Requires-Dist: x-transformers (<1.0,>=0.20)
Requires-Dist: ecco (==0.0.14)
Requires-Dist: transformers (~=4.11.3)
